CHANGES.txt
MANIFEST.in
README.rst
setup.cfg
setup.py
Solgema/__init__.py
Solgema.PortletsManager.egg-info/PKG-INFO
Solgema.PortletsManager.egg-info/SOURCES.txt
Solgema.PortletsManager.egg-info/dependency_links.txt
Solgema.PortletsManager.egg-info/entry_points.txt
Solgema.PortletsManager.egg-info/namespace_packages.txt
Solgema.PortletsManager.egg-info/not-zip-safe
Solgema.PortletsManager.egg-info/requires.txt
Solgema.PortletsManager.egg-info/top_level.txt
Solgema/PortletsManager/README.txt
Solgema/PortletsManager/__init__.py
Solgema/PortletsManager/config.py
Solgema/PortletsManager/configure.zcml
Solgema/PortletsManager/exportimport.py
Solgema/PortletsManager/interfaces.py
Solgema/PortletsManager/options.py
Solgema/PortletsManager/profiles.zcml
Solgema/PortletsManager/setuphandlers.py
Solgema/PortletsManager/versions.txt
Solgema/PortletsManager/Extensions/Install.py
Solgema/PortletsManager/Extensions/__init__.py
Solgema/PortletsManager/locales/Solgema.PortletsManager.pot
Solgema/PortletsManager/locales/update.sh
Solgema/PortletsManager/locales/en/LC_MESSAGES/Solgema.PortletsManager.mo
Solgema/PortletsManager/locales/en/LC_MESSAGES/Solgema.PortletsManager.po
Solgema/PortletsManager/locales/fr/LC_MESSAGES/Solgema.PortletsManager.mo
Solgema/PortletsManager/locales/fr/LC_MESSAGES/Solgema.PortletsManager.po
Solgema/PortletsManager/locales/it/LC_MESSAGES/Solgema.PortletsManager.mo
Solgema/PortletsManager/locales/it/LC_MESSAGES/Solgema.PortletsManager.po
Solgema/PortletsManager/locales/no/LC_MESSAGES/Solgema.PortletsManager.mo
Solgema/PortletsManager/locales/no/LC_MESSAGES/Solgema.PortletsManager.po
Solgema/PortletsManager/portlets/__init__.py
Solgema/PortletsManager/portlets/adapters.py
Solgema/PortletsManager/portlets/column.pt
Solgema/PortletsManager/portlets/configure.zcml
Solgema/PortletsManager/portlets/editmanager.py
Solgema/PortletsManager/portlets/herited-manager-macros.pt
Solgema/PortletsManager/portlets/manager.py
Solgema/PortletsManager/portlets/retriever.py
Solgema/PortletsManager/portlets/solgema-edit-manager-contextual.pt
Solgema/PortletsManager/portlets/solgema-manage-contextual.pt
Solgema/PortletsManager/portlets/solgema-manage-contextual.pt~
Solgema/PortletsManager/portlets/solgemaportletsmanager.css
Solgema/PortletsManager/portlets/view.py
Solgema/PortletsManager/profiles/default/browserlayer.xml
