Metadata-Version: 1.1
Name: Solgema.PortletsManager
Version: 1.1
Summary: Solgema Portlets Manager
Home-page: http://www.martronic.ch/plone_products/Solgema.PortletsManager
Author: Martronic SA
Author-email: martronic@martronic.ch
License: GPL
Keywords: Solgema
Platform: UNKNOWN
Classifier: Framework :: Plone
Classifier: Programming Language :: Python
Classifier: Topic :: Software Development :: Libraries :: Python Modules
